setup.py
dm_interface.egg-info/PKG-INFO
dm_interface.egg-info/SOURCES.txt
dm_interface.egg-info/dependency_links.txt
dm_interface.egg-info/requires.txt
dm_interface.egg-info/top_level.txt
interface/__init__.py
interface/client.py