Metadata-Version: 1.0
Name: dm-interface
Version: 1.0.2
Summary: The interface to download and upload files using WebDAV or IPFS.
Home-page: UNKNOWN
Author: UNKNOWN
Author-email: UNKNOWN
License: MIT
Platform: UNKNOWN
